oxt_generator/README_extension_owner.txt
oxt_generator/__init__.py
oxt_generator/cli_app.py
oxt_generator/en_US_private.aff
oxt_generator/file_generator.py
oxt_generator/license.txt
oxt_generator/package.py
oxt_generator/word_list.py
oxt_generator-0.0.2.dist-info/entry_points.txt
oxt_generator-0.0.2.dist-info/LICENSE
oxt_generator-0.0.2.dist-info/WHEEL
oxt_generator-0.0.2.dist-info/METADATA
oxt_generator-0.0.2.dist-info/RECORD
