Metadata-Version: 2.1
Name: oxt_generator
Version: 0.0.2
Summary: Generates `.oxt` files from custom wordlists
Author-email: Arun Kishore <pypi@rpakishore.co.in>
Classifier: License :: OSI Approved :: MIT License
Requires-Dist: pytest>=7.2.1
Requires-Dist: typer[all]
Project-URL: Home, https://github.com/rpakishore/oxt-custom_dict
